yandex_yadoctool/__init__.py
yandex_yadoctool/main.py
yandex_yadoctool/operations/__init__.py
yandex_yadoctool/operations/corrector.py
yandex_yadoctool/operations/keyrefs.py
yandex_yadoctool/operations/locales.py
yandex_yadoctool-1.11.dist-info/METADATA
yandex_yadoctool-1.11.dist-info/WHEEL
yandex_yadoctool-1.11.dist-info/entry_points.txt
yandex_yadoctool-1.11.dist-info/top_level.txt
yandex_yadoctool-1.11.dist-info/RECORD
