Metadata-Version: 2.1
Name: yandex-yadoctool
Version: 1.11
Summary: Dita-docs tool
Home-page: UNKNOWN
Author-email: anokhin-b@yandex-team.ru
License: UNKNOWN
Platform: UNKNOWN
Requires-Python: >3.5.2
Requires-Dist: requests
